vbgpt/__init__.py
vbgpt/__main__.py
vbgpt/choice_option.py
vbgpt/main.py
vbgpt-0.1.5.dist-info/METADATA
vbgpt-0.1.5.dist-info/WHEEL
vbgpt-0.1.5.dist-info/entry_points.txt
vbgpt-0.1.5.dist-info/RECORD
