Metadata-Version: 2.1
Name: vbgpt
Version: 0.1.5
Summary: 
Author: vaibhavblayer
Author-email: vaibhavblayer@gmail.com
Requires-Python: >=3.12,<4.0
Classifier: Programming Language :: Python :: 3
Classifier: Programming Language :: Python :: 3.12
Requires-Dist: click (>=8.1.7,<9.0.0)
